mcp_standalone/__init__.py
mcp_standalone/cli.py
mcp_standalone/config.py
mcp_standalone/sse_client.py
mcp_standalone-0.1.0.dist-info/METADATA
mcp_standalone-0.1.0.dist-info/WHEEL
mcp_standalone-0.1.0.dist-info/entry_points.txt
mcp_standalone-0.1.0.dist-info/top_level.txt
mcp_standalone-0.1.0.dist-info/RECORD
