Metadata-Version: 2.4
Name: mcp-standalone
Version: 0.1.0
Summary: A standalone MCP client without external dependencies
Author: David Schwartz
License-Expression: MIT
Requires-Python: >=3.8
Requires-Dist: httpx>=0.27
Requires-Dist: httpx-sse>=0.4
Requires-Dist: anyio>=4.5
Requires-Dist: pydantic<3.0.0,>=2.7.2
Requires-Dist: pydantic-settings>=2.5.2
